plombery/__init__.py
plombery/_version.py
plombery/constants.py
plombery/schemas.py
plombery/utils.py
plombery/api/__init__.py
plombery/api/authentication.py
plombery/api/middlewares.py
plombery/api/routers/__init__.py
plombery/api/routers/pipelines.py
plombery/api/routers/runs.py
plombery/api/routers/websocket.py
plombery/config/__init__.py
plombery/config/model.py
plombery/config/parser.py
plombery/config/yaml_loader.py
plombery/database/__init__.py
plombery/database/base.py
plombery/database/models.py
plombery/database/repository.py
plombery/database/schemas.py
plombery/logger/__init__.py
plombery/logger/formatter.py
plombery/logger/web_socket_handler.py
plombery/notifications/__init__.py
plombery/notifications/helpers.py
plombery/notifications/templates.py
plombery/notifications/email_templates/transactional.html
plombery/notifications/email_templates/images/.gitkeep
plombery/orchestrator/__init__.py
plombery/orchestrator/data_storage.py
plombery/orchestrator/executor.py
plombery/pipeline/__init__.py
plombery/pipeline/_utils.py
plombery/pipeline/context.py
plombery/pipeline/pipeline.py
plombery/pipeline/task.py
plombery/pipeline/trigger.py
plombery/static/index.html
plombery/static/mario-pipe-flower.png
plombery/static/assets/HandsonTable-BL5bSNAs.js
plombery/static/assets/HandsonTable-CeXsD9Sv.css
plombery/static/assets/index-BO_mHXQm.css
plombery/static/assets/index-BdrMhwXz.js
plombery/static/assets/vendor-RR7AYvzk.js
plombery/websocket/__init__.py
plombery_chinese-0.4.1.dist-info/LICENSE
plombery_chinese-0.4.1.dist-info/METADATA
plombery_chinese-0.4.1.dist-info/WHEEL
plombery_chinese-0.4.1.dist-info/top_level.txt
plombery_chinese-0.4.1.dist-info/RECORD
